harfang-3.2.7.data/purelib/harfang/__init__.py
harfang-3.2.7.data/purelib/harfang/glfw3.dll
harfang-3.2.7.data/purelib/harfang/harfang.pyd
harfang-3.2.7.data/purelib/harfang/lua54.dll
harfang-3.2.7.data/purelib/harfang/openvr_api.dll
harfang-3.2.7.data/purelib/harfang/bin/__init__.py
harfang-3.2.7.data/purelib/harfang/bin/__main__.py
harfang-3.2.7.data/purelib/harfang/bin/run.py
harfang-3.2.7.data/purelib/harfang/bin/assetc/assetc.exe
harfang-3.2.7.data/purelib/harfang/bin/assetc/glfw3.dll
harfang-3.2.7.data/purelib/harfang/bin/assetc/lua54.dll
harfang-3.2.7.data/purelib/harfang/bin/assetc/openvr_api.dll
harfang-3.2.7.data/purelib/harfang/bin/assetc/toolchains/host-windows-x64-target-windows-x64/bulletc.exe
harfang-3.2.7.data/purelib/harfang/bin/assetc/toolchains/host-windows-x64-target-windows-x64/cmft.exe
harfang-3.2.7.data/purelib/harfang/bin/assetc/toolchains/host-windows-x64-target-windows-x64/luac.exe
harfang-3.2.7.data/purelib/harfang/bin/assetc/toolchains/host-windows-x64-target-windows-x64/recastc.exe
harfang-3.2.7.data/purelib/harfang/bin/assetc/toolchains/host-windows-x64-target-windows-x64/shaderc.exe
harfang-3.2.7.data/purelib/harfang/bin/assetc/toolchains/host-windows-x64-target-windows-x64/texconv.exe
harfang-3.2.7.data/purelib/harfang/bin/assetc/toolchains/host-windows-x64-target-windows-x64/texturec.exe
harfang-3.2.7.dist-info/METADATA
harfang-3.2.7.dist-info/WHEEL
harfang-3.2.7.dist-info/top_level.txt
harfang-3.2.7.dist-info/RECORD
