Metadata-Version: 2.1
Name: harfang
Version: 3.2.7
Summary: HARFANG 3D is a game/visualization library for Python. It includes a comprehensive set of Scene, Physics, Rendering pipeline, Audio and Virtual Reality APIs. It is written in C++ and supports DirectX 11, OpenGL and OpenGL ES.
Home-page: https://www.harfang3d.com
Author: NWNC HARFANG
Author-email: contact@harfang3d.com
License: Other/Proprietary License
Project-URL: Changelog, https://github.com/harfang3d/harfang3d/releases/tag/v3.2.7
Project-URL: Documentation, https://www.harfang3d.com/api/3.2.7/cpython/classes/
Project-URL: Source, https://github.com/harfang3d/harfang3d
Project-URL: Tracker, https://github.com/harfang3d/harfang3d/issues
Keywords: 2d 3d multimedia development engine realtime rendering design visualization simulation physics vr virtual reality python lua opengl opengles directx
Classifier: Intended Audience :: Developers
Classifier: Intended Audience :: Science/Research
Classifier: Topic :: Software Development
Classifier: Topic :: Software Development :: Libraries :: Application Frameworks
Classifier: Topic :: Multimedia :: Sound/Audio
Classifier: Topic :: Multimedia :: Graphics :: 3D Rendering
Classifier: Topic :: Scientific/Engineering :: Visualization
Classifier: Operating System :: POSIX
Classifier: Operating System :: POSIX :: Linux
Classifier: Operating System :: Microsoft
Classifier: Operating System :: Microsoft :: Windows
Classifier: Programming Language :: Python :: 3
Requires-Python: >3.6
